notix/__init__.py
notix/constants.py
notix/exceptions.py
notix/notix_api.py
notix_python-0.1.0.dist-info/LICENSE
notix_python-0.1.0.dist-info/METADATA
notix_python-0.1.0.dist-info/WHEEL
notix_python-0.1.0.dist-info/top_level.txt
notix_python-0.1.0.dist-info/RECORD
