Metadata-Version: 2.1
Name: notix-python
Version: 0.1.0
Summary: Python Notix Push notification wrapper
Home-page: https://github.com/shreyanshu7101904/notix-push-notification
Author: Shreyanshu Shankar
Author-email: shreyanshu7101904@gmail.com
License: UNKNOWN
Platform: UNKNOWN
License-File: LICENSE
Requires-Dist: requests
